setup.py
fio/__init__.py
fio/scrape.py
python_fio.egg-info/PKG-INFO
python_fio.egg-info/SOURCES.txt
python_fio.egg-info/dependency_links.txt
python_fio.egg-info/top_level.txt