Metadata-Version: 1.1
Name: python-fio
Version: 0.1
Summary: Fio bank account data scraper
Home-page: https://github.com/hackerspace/python-fio
Author: Richard Marko
Author-email: rissko@gmail.com
License: GPL
Platform: UNKNOWN
Classifier: Development Status :: 4 - Beta
Classifier: Intended Audience :: Developers
Classifier: Operating System :: OS Independent
Classifier: Programming Language :: Python
